dtocean_qt/__init__.py
dtocean_qt-0.10.1.dist-info/METADATA
dtocean_qt-0.10.1.dist-info/WHEEL
dtocean_qt-0.10.1.dist-info/RECORD
